main.py
mcp_eval-0.0.1.dist-info/licenses/LICENSE
mcp_eval-0.0.1.dist-info/METADATA
mcp_eval-0.0.1.dist-info/WHEEL
mcp_eval-0.0.1.dist-info/top_level.txt
mcp_eval-0.0.1.dist-info/RECORD
