Metadata-Version: 2.4
Name: mcp-eval
Version: 0.0.1
Summary: Evaluate MCP models
Requires-Python: >=3.12
License-File: LICENSE
Dynamic: license-file
